Workbook

Sheet Dashboard
A1: SENGO FINANCIAL DASHBOARD
A2: Summary view — all cells driven by model
B4: 2025 | C4: 2026 | D4: 2027 | E4: 2028
A5: Total Revenue | B5: =Projections!B34 -> 194681 | C5: =Projections!C34 -> 315346 | D5: =Projections!D34 -> 797530 | E5: =Projections!E34 -> 1769500
A6: Revenue Growth % | C6: =IF(B5>0,(C5-B5)/B5,0) -> 0.61980882 | D6: =IF(C5>0,(D5-C5)/C5,0) -> 1.5290633 | E6: =IF(D5>0,(E5-D5)/D5,0) -> 1.2187253
A7: Gross Profit | B7: =Projections!B36 -> 176575.67 | C7: =Projections!C36 -> 283811.4 | D7: =Projections!D36 -> 717777 | E7: =Projections!E36 -> 1610245
A8: Gross Margin | B8: =Projections!B37 -> 0.907 | C8: =Projections!C37 -> 0.9 | D8: =Projections!D37 -> 0.9 | E8: =Projections!E37 -> 0.91
A9: Operating Income | B9: =Projections!B39 -> 80575.667 | C9: =Projections!C39 -> -214188.6 | D9: =Projections!D39 -> -60223 | E9: =Projections!E39 -> 590245
A10: Operating Margin | B10: =Projections!B40 -> 0.41388562 | C10: =Projections!C40 -> -0.67921775 | D10: =Projections!D40 -> -0.075511893 | E10: =Projections!E40 -> 0.33356598
A11: Debt Service | B11: =Projections!B44 -> 0 | C11: =Projections!C44 -> -39506.94 | D11: =Projections!D44 -> -63616.14 | E11: =Projections!E44 -> -112214.64
A12: Net Income | B12: =Projections!B45 -> 80575.667 | C12: =Projections!C45 -> -253695.54 | D12: =Projections!D45 -> -123839.14 | E12: =Projections!E45 -> 478030.36
A13: Cash Position | B13: =Projections!B48 -> 85575.667 | C13: =Projections!C48 -> 331880.13 | D13: =Projections!D48 -> 208040.99 | E13: =Projections!E48 -> 686071.35
A15: SaaS Subscribers | B15: =Assumptions!B75 -> 132 | C15: =Assumptions!C75 -> 515 | D15: =Assumptions!D75 -> 1650 | E15: =Assumptions!E75 -> 3600
A16: Coaching Clients | B16: =Assumptions!B76 -> 4 | C16: =Assumptions!C76 -> 6 | D16: =Assumptions!D76 -> 15 | E16: =Assumptions!E76 -> 33
A17: Email Subscribers | B17: =Assumptions!B77 -> 10000 | C17: =Assumptions!C77 -> 25000 | D17: =Assumptions!D77 -> 60000 | E17: =Assumptions!E77 -> 120000
A18: LTV:CAC | B18: =Assumptions!B82 -> 7.0243056 | C18: =Assumptions!C82 -> 3.0979591 | D18: =Assumptions!D82 -> 6.8445683 | E18: =Assumptions!E82 -> 11.567575
A20: Implied Valuation (8x Rev) | B20: ='Valuation & Exit'!B12 -> 1557448 | C20: ='Valuation & Exit'!C12 -> 2522768 | D20: ='Valuation & Exit'!D12 -> 6380240 | E20: ='Valuation & Exit'!E12 -> 14156000
A22: FUNDRAISE SCENARIO | C22: Change blue cells below — model updates automatically
A23: SAFE Investment Amount | B23: 250000 | C23: Portion of raise structured as SAFE
A24: RBF Investment Amount | B24: 150000 | C24: Portion structured as revenue-based financing
A25: CDFI Loan Amount | B25: 100000 | C25: Portion structured as CDFI loan
A26: Total Raise | B26: =B23+B24+B25 -> 500000 | C26: SAFE + RBF + CDFI
A28: RBF Revenue Share % | B28: 0.05 | C28: Typical 3-8% of monthly revenue
A29: RBF Repayment Cap (multiple) | B29: 1.5 | C29: Max repayment = investment x cap
A30: CDFI Interest Rate | B30: 0.06 | C30: CDFI rates typically 4-8%
A31: CDFI Loan Term (years) | B31: 5 | C31: Typical 3-7 year term
A32: SAFE Valuation Cap | B32: 5000000 | C32: Pre-money cap on SAFE note
A34: SAFE Equity Dilution | B34: =IF(B32>0,B23/B32,0) -> 0.05
A35: RBF Max Repayment | B35: =B24*B29 -> 225000
A36: CDFI Annual Payment (PMT) | B36: =PMT(B30,B31,-B25) -> 23739.64
A37: Annual Debt Service (2026 est.) | B37: =Projections!C44 -> -39506.94
A38: Founder Ownership Retained | B38: =1-B34 -> 0.95
A40: HOW TO REVIEW THIS MODEL
A41: 1. Start here on the Dashboard | B41: This tab summarizes the full model. Scroll down to adjust the fundraise scenario.
A42: 2. Adjust the fundraise mix above | B42: Change SAFE, RBF, and CDFI amounts in the blue cells (rows 23-25). Change the valuation cap (row 32). All downstream tabs update automatically: debt service, valuations, cash position, and net income.
A43: 3. Review the Assumptions tab | B43: All revenue projections, expense budgets, and growth targets are here. Blue cells are editable. Expand collapsed rows (+) to see product-level and role-level detail.
A44: 4. Check the 2026 Monthly P&L | B44: January and February are QuickBooks actuals (blue columns). March onward is budget (yellow columns). This is your real-time pulse on how 2026 is tracking.
A45: 5. Review the Projections tab | B45: 3-year P&L pulling from Assumptions. Includes a Debt Service section (RBF + CDFI payments) between Operating Income and Net Income. Cash Position includes the pre-seed raise.
A46: 6. Compare Bootstrapped scenario | B46: Shows what growth looks like without raising. Always profitable but slower. Side-by-side comparison to the funded scenario at the bottom.
A47: 7. Explore Valuation & Exit | B47: Revenue and income multiples, three SAFE cap scenarios (including your target cap from row 32), full RBF repayment schedule, CDFI amortization, and combined fund structure. All driven by the inputs you set on this Dashboard.
A49: TIP | B49: Try different SAFE/RBF/CDFI splits and valuation caps above — watch how Net Income, Cash Position, dilution, and Valuation change across the model. The debt service flows through Projections into the Valuation tab.

Sheet Assumptions
A1: SENGO FINANCIAL MODEL
A2: Assumptions & Inputs
A3: Blue = editable | Expand rows for product/role detail
B5: 2025 (Actual) | C5: 2026 (Proj) | D5: 2027 (Proj) | E5: 2028 (Proj) | F5: Notes / Source
A6: REVENUE ASSUMPTIONS
A7: SaaS Annual Revenue | B7: =SUM(B9,B11,B13,B15) -> 18230 | C7: =SUM(C9,C11,C13,C15) -> 59346 | D7: =SUM(D9,D11,D13,D15) -> 205530 | E7: =SUM(E9,E11,E13,E15) -> 502500 | F7: Sum of 4 tier revenues below
A8: Legacy Subscribers ($7/mo) | B8: 13 | C8: 15 | D8: 0 | E8: 0 | F8: Original tier; 13 current (Mar '26). Phased out after 2026
A9: Legacy Annual Revenue | B9: 1100 | C9: =(B8+C8)/2*7*12 -> 1176 | D9: =(C8+D8)/2*7*12 -> 630 | E9: =(D8+E8)/2*7*12 -> 0
A10: Investor Subscribers ($10/mo) | B10: 4 | C10: 40 | D10: 200 | E10: 500 | F10: 4 current (Mar '26); curated deal flow
A11: Investor Annual Revenue | B11: 400 | C11: =(B10+C10)/2*10*12 -> 2640 | D11: =(C10+D10)/2*10*12 -> 14400 | E11: =(D10+E10)/2*10*12 -> 42000
A12: Founder Subscribers ($15/mo) | B12: 112 | C12: 400 | D12: 1200 | E12: 2500 | F12: 112 current (Mar '26); primary growth tier
A13: Founder Annual Revenue | B13: 15830 | C13: =(B12+C12)/2*15*12 -> 46080 | D13: =(C12+D12)/2*15*12 -> 144000 | E13: =(D12+E12)/2*15*12 -> 333000
A14: All Access Subscribers ($25/mo) | B14: 3 | C14: 60 | D14: 250 | E14: 600 | F14: 3 current (Mar '26); full platform access
A15: All Access Annual Revenue | B15: 900 | C15: =(B14+C14)/2*25*12 -> 9450 | D15: =(C14+D14)/2*25*12 -> 46500 | E15: =(D14+E14)/2*25*12 -> 127500
A17: Coaching Annual Revenue | B17: =SUM(B19,B21,B23,B24) -> 2000 | C17: =SUM(C19,C21,C23,C24) -> 79000 | D17: =SUM(D19,D21,D23,D24) -> 177000 | E17: =SUM(E19,E21,E23,E24) -> 420000 | F17: Sum of tier revenues + deferred payouts
A18: Legacy Clients ($500/mo) | B18: 2 | C18: 1 | D18: 0 | E18: 0 | F18: Phasing out legacy tier
A19: Legacy Annual Revenue | B19: 1000 | C19: =(B18+C18)/2*500*12 -> 9000 | D19: =(C18+D18)/2*500*12 -> 3000 | E19: =(D18+E18)/2*500*12 -> 0
A20: Foundation Clients ($1,000/mo) | B20: 1 | C20: 3 | D20: 8 | E20: 18 | F20: Deferred payment plans available; $500/mo til first check
A21: Foundation Annual Revenue | B21: 500 | C21: =(B20+C20)/2*1000*12 -> 24000 | D21: =(C20+D20)/2*1000*12 -> 66000 | E21: =(D20+E20)/2*1000*12 -> 156000
A22: Accelerator Clients ($2,000/mo) | B22: 1 | C22: 2 | D22: 7 | E22: 15 | F22: Deferred payment plans available
A23: Accelerator Annual Revenue | B23: 500 | C23: =(B22+C22)/2*2000*12 -> 36000 | D23: =(C22+D22)/2*2000*12 -> 108000 | E23: =(D22+E22)/2*2000*12 -> 264000
A24: Deferred Coaching Payouts | B24: 0 | C24: 10000 | D24: 0 | E24: 0 | F24: $10K March 2026 payout from deferred client payments
A25: Events & Sales Revenue | B25: 70640 | C25: =SUM(C26:C32) -> 87000 | D25: =SUM(D26:D32) -> 140000 | E25: =SUM(E26:E32) -> 212000 | F25: 2025 actual from P&L ($3,250 reclassified to B2B); 2026+ sum of events below
A26: FxF NYC (Feb) | B26: 0 | C26: 17000 | D26: 25000 | E26: 35000 | F26: Vendor fees + brand rev (gross)
A27: NY Tech Week (June) | B27: 0 | C27: 5000 | D27: 8000 | E27: 12000 | F27: Smaller activation; thin margins, growing YoY
A28: FxF LA (June) | B28: 0 | C28: 10000 | D28: 16000 | E28: 24000
A29: FxF NYC (Sept) | B29: 0 | C29: 14000 | D29: 22000 | E29: 32000
A30: FxF LA (Nov) | B30: 0 | C30: 10000 | D30: 16000 | E30: 24000
A31: Other In-Person (3 TBD) | B31: 0 | C31: 21000 | D31: 33000 | E31: 50000 | F31: ~$7K avg per event
A32: Virtual Events | B32: 0 | C32: 10000 | D32: 20000 | E32: 35000 | F32: Workshops, webinars, panels
A34: B2B / Sponsorship Revenue | B34: =SUM(B35:B39) -> 18250 | C34: =SUM(C35:C39) -> 50000 | D34: =SUM(D35:D39) -> 255000 | E34: =SUM(E35:E39) -> 635000 | F34: Sum of sponsorship tiers; see 2026 Monthly P&L for actuals
A35: Event Partners ($10K-$25K) | B35: 0 | C35: 30000 | D35: 100000 | E35: 200000 | F35: Brand awareness, speaking opps, attendee access
A36: Media Partners ($2K-$5K) | B36: 0 | C36: 10000 | D36: 30000 | E36: 60000 | F36: Newsletter placements, content collabs, touchpoints
A37: Platform Partners ($10K-$50K) | B37: 0 | C37: 10000 | D37: 50000 | E37: 150000 | F37: Dealflow access, priority founder intros
A38: Ecosystem Partners ($75K+) | B38: 0 | C38: 0 | D38: 75000 | E38: 225000 | F38: Multi-channel, co-created programming
A39: Partner Deployments | B39: 18250 | C39: 0 | D39: 0 | E39: 0 | F39: Partner deployments ($15K) + sponsorships ($3,250) reclassified from Events/Grants
A40: Grant Revenue | B40: 37156 | C40: 40000 | D40: 20000 | E40: 0 | F40: BGV Emerging Leaders Fellowship + W.E. Build in Tulsa Cohort (2025); reduced $17.5K; declining as recurring revenue grows
A41: Services & Consulting | B41: 48405 | C41: 0 | D41: 0 | E41: 0 | F41: 2025 only (IBC parent co); phased out
A43: COST ASSUMPTIONS
A44: COGS % of Revenue | B44: 0.093 | C44: 0.1 | D44: 0.1 | E44: 0.09 | F44: Source: P&L 2025 (9.3% actual)
A46: OPERATING EXPENSE DETAIL
A47: Personnel | B47: =SUM(B48:B53) -> 17000 | C47: =SUM(C48:C53) -> 180000 | D47: =SUM(D48:D53) -> 340000 | E47: =SUM(E48:E53) -> 480000 | F47: Payroll + contract labor
A48: Founder / CEO (Ila) | B48: 7911 | C48: 60000 | D48: 75000 | E48: 90000 | F48: Current; salary begins 2026
A49: Engineering Lead | B49: 0 | C49: 65000 | D49: 80000 | E49: 95000 | F49: Hire Q2 2026; platform build
A50: Sales / BD Lead | B50: 0 | C50: 45000 | D50: 60000 | E50: 75000 | F50: Hire Q3 2026; partnerships + coaching sales
A51: Marketing Manager | B51: 0 | C51: 0 | D51: 50000 | E51: 60000 | F51: Hire 2027; content, social, campaigns
A52: Operations / Support | B52: 0 | C52: 0 | D52: 0 | E52: 50000 | F52: Hire 2028; admin, customer success
A53: Contract Labor | B53: 9089 | C53: 10000 | D53: 75000 | E53: 110000 | F53: Design, dev, content contractors
A54: Technology & Platform | B54: =SUM(B55:B56) -> 12000 | C54: =SUM(C55:C56) -> 85000 | D54: =SUM(D55:D56) -> 120000 | E54: =SUM(E55:E56) -> 150000 | F54: Software, hosting, infrastructure
A55: Software & Apps | B55: 8197 | C55: 45000 | D55: 60000 | E55: 75000 | F55: Platform tools, APIs, subscriptions
A56: Platform Infrastructure | B56: 3803 | C56: 40000 | D56: 60000 | E56: 75000 | F56: Hosting, CDN, AI compute, DevOps
A57: Marketing & Growth | B57: =SUM(B58:B62) -> 8000 | C57: =SUM(C58:C62) -> 110000 | D57: =SUM(D58:D62) -> 160000 | E57: =SUM(E58:E62) -> 200000 | F57: Sum of marketing channels below
A58: Conferences & Speaking | B58: 1500 | C58: 20000 | D58: 30000 | E58: 40000 | F58: Event booths, sponsorships, speaker travel
A59: Social Media & Content | B59: 2000 | C59: 25000 | D59: 35000 | E59: 45000 | F59: Content creation, social mgmt, video
A60: Paid Ads (Digital) | B60: 500 | C60: 35000 | D60: 50000 | E60: 60000 | F60: Meta, Google, LinkedIn campaigns
A61: PR & Brand Campaigns | B61: 2000 | C61: 20000 | D61: 30000 | E61: 40000 | F61: Press, influencer partnerships, brand
A62: Community Grants | B62: 2000 | C62: 10000 | D62: 15000 | E62: 15000 | F62: Micro-grants to founders in community
A63: Events & Community | B63: =SUM(B64:B65) -> 42000 | C63: =SUM(C64:C65) -> 60000 | D63: =SUM(D64:D65) -> 80000 | E63: =SUM(E64:E65) -> 100000 | F63: Event production + community programs
A64: Event Production | B64: 37000 | C64: 50000 | D64: 65000 | E64: 80000 | F64: Venue, production, brand pass-through
A65: Community Programs | B65: 5000 | C65: 10000 | D65: 15000 | E65: 20000 | F65: Member programs, retreats, networking
A66: Compliance & Legal | B66: 5000 | C66: 45000 | D66: 50000 | E66: 55000 | F66: Reg CF/D advisory, legal, accounting
A67: Operations & Admin | B67: 12000 | C67: 18000 | D67: 28000 | E67: 35000 | F67: Travel, benefits, insurance, general overhead
A68: Total Operating Expenses | B68: =B47+B54+B57+B63+B66+B67 -> 96000 | C68: =C47+C54+C57+C63+C66+C67 -> 498000 | D68: =D47+D54+D57+D63+D66+D67 -> 778000 | E68: =E47+E54+E57+E63+E66+E67 -> 1020000
A70: FUNDRAISE & CASH FLOW
A71: Pre-Seed Investment | B71: 0 | C71: =Dashboard!B26 -> 500000 | D71: 0 | E71: 0 | F71: SAFE + RBF + CDFI — driven by Dashboard
A72: Starting Cash Balance | B72: 5000 | C72: =Projections!B48 -> 85575.667 | D72: =Projections!C48 -> 331880.13 | E72: =Projections!D48 -> 208040.99 | F72: Prior year ending cash
A74: GROWTH & KPI TARGETS
A75: Total SaaS Subscribers (EOY) | B75: =B8+B10+B12+B14 -> 132 | C75: =C8+C10+C12+C14 -> 515 | D75: =D8+D10+D12+D14 -> 1650 | E75: =E8+E10+E12+E14 -> 3600 | F75: Sum of all 4 SaaS tiers
A76: Total Coaching Clients (EOY) | B76: =B18+B20+B22 -> 4 | C76: =C18+C20+C22 -> 6 | D76: =D18+D20+D22 -> 15 | E76: =E18+E20+E22 -> 33
A77: Email Subscribers | B77: 10000 | C77: 25000 | D77: 60000 | E77: 120000
A78: Email → Paid Conversion Rate | B78: 0.014 | C78: 0.024 | D78: 0.033 | E78: 0.042
A79: CAC (Blended) | B79: =IF((B75+B76)>0,B57/(B75+B76),0) -> 58.823529 | C79: =IF((C75+C76)-(B75+B76)>0,C57/((C75+C76)-(B75+B76)),0) -> 285.71429 | D79: =IF((D75+D76)-(C75+C76)>0,D57/((D75+D76)-(C75+C76)),0) -> 139.86014 | E79: =IF((E75+E76)-(D75+D76)>0,E57/((E75+E76)-(D75+D76)),0) -> 101.62602 | F79: Marketing Spend / New Customers (SaaS + Coaching)
A80: Monthly Churn Rate | B80: 0.03 | C80: 0.025 | D80: 0.02 | E80: 0.018 | F80: Assumption (blue input); improves as community retention strengthens
A81: LTV (Blended) | B81: =IF(AND(B80>0,(B75+B76)>0),(B7+B17)/(B75+B76)/12/B80,0) -> 413.19444 | C81: =IF(AND(C80>0,(C75+C76)>0),(C7+C17)/(C75+C76)/12/C80,0) -> 885.13116 | D81: =IF(AND(D80>0,(D75+D76)>0),(D7+D17)/(D75+D76)/12/D80,0) -> 957.28228 | E81: =IF(AND(E80>0,(E75+E76)>0),(E7+E17)/(E75+E76)/12/E80,0) -> 1175.5666 | F81: Blended ARPU (SaaS + Coaching) / Monthly Churn
A82: LTV:CAC Ratio | B82: =IF(B79>0,B81/B79,0) -> 7.0243056 | C82: =IF(C79>0,C81/C79,0) -> 3.0979591 | D82: =IF(D79>0,D81/D79,0) -> 6.8445683 | E82: =IF(E79>0,E81/E79,0) -> 11.567575 | F82: LTV / CAC; investors look for 3x+
A83: ARPU (Monthly, Blended) | B83: =IF((B75+B76)>0,(B7+B17)/(B75+B76)/12,0) -> 12.395833 | C83: =IF((C75+C76)>0,(C7+C17)/(C75+C76)/12,0) -> 22.128279 | D83: =IF((D75+D76)>0,(D7+D17)/(D75+D76)/12,0) -> 19.145646 | E83: =IF((E75+E76)>0,(E7+E17)/(E75+E76)/12,0) -> 21.160198 | F83: (SaaS Rev + Coaching Rev) / Total Customers / 12
A84: New Customers Acquired | B84: =B75+B76 -> 136 | C84: =(C75+C76)-(B75+B76) -> 385 | D84: =(D75+D76)-(C75+C76) -> 1144 | E84: =(E75+E76)-(D75+D76) -> 1968 | F84: Net new SaaS + Coaching customers YoY
A86: NOTE: 2026 blended CAC is $286 because marketing spend ($110K) includes brand-building, PR, conferences, and community grants alongside direct acquisition. We report the full blended number conservatively — attributing all marketing spend to customer acquisition rather than splitting out brand awareness. As organic channels compound (10K→120K email subscribers, community referrals, press coverage), CAC drops to $102 by 2028. LTV:CAC improves from 3.1x to 11.6x, well above the 3x benchmark.

Sheet Raise Progression
A1: SENGO RAISE PROGRESSION
A2: Map investments received against planned deployments — blue cells are editable
B4: Apr '26 | C4: May '26 | D4: Jun '26 | E4: Jul '26 | F4: Aug '26 | G4: Sep '26 | H4: Oct '26 | I4: Nov '26 | J4: Dec '26 | K4: Jan '27 | L4: Feb '27 | M4: Mar '27 | N4: TOTAL | O4: Notes / Source
A5: CAPITAL INFLOWS
A6: SAFE Checks Received | B6: 0 | C6: 0 | D6: 0 | E6: 0 | F6: 0 | G6: 0 | H6: 0 | I6: 0 | J6: 0 | K6: 0 | L6: 0 | M6: 0 | N6: =SUM(B6:M6) -> 0 | O6: Enter each SAFE check as it closes
A7: RBF Funding Received | B7: 0 | C7: 0 | D7: 0 | E7: 0 | F7: 0 | G7: 0 | H7: 0 | I7: 0 | J7: 0 | K7: 0 | L7: 0 | M7: 0 | N7: =SUM(B7:M7) -> 0 | O7: Revenue-based financing disbursement(s)
A8: CDFI Loan Disbursement | B8: 0 | C8: 0 | D8: 0 | E8: 0 | F8: 0 | G8: 0 | H8: 0 | I8: 0 | J8: 0 | K8: 0 | L8: 0 | M8: 0 | N8: =SUM(B8:M8) -> 0 | O8: CDFI loan disbursement(s)
A9: Operating Revenue (from model) | B9: ='2026 Monthly P&L'!B11 -> 9844 | C9: ='2026 Monthly P&L'!C11 -> 9300 | D9: ='2026 Monthly P&L'!D11 -> 15886 | E9: ='2026 Monthly P&L'!E11 -> 12548.191 | F9: ='2026 Monthly P&L'!F11 -> 19449.683 | G9: ='2026 Monthly P&L'!G11 -> 56871.266 | H9: ='2026 Monthly P&L'!H11 -> 25523.398 | I9: ='2026 Monthly P&L'!I11 -> 17052.027 | ... M9: ='2026 Monthly P&L'!M11 -> 25414.288 | N9: =SUM(B9:M9) -> 315346 | O9: Monthly rev from 2026 Monthly P&L
A10: Total New Capital This Month | B10: =B6+B7+B8+B9 -> 9844 | C10: =C6+C7+C8+C9 -> 9300 | D10: =D6+D7+D8+D9 -> 15886 | E10: =E6+E7+E8+E9 -> 12548.191 | F10: =F6+F7+F8+F9 -> 19449.683 | G10: =G6+G7+G8+G9 -> 56871.266 | H10: =H6+H7+H8+H9 -> 25523.398 | I10: =I6+I7+I8+I9 -> 17052.027 | ... M10: =M6+M7+M8+M9 -> 25414.288 | N10: =SUM(B10:M10) -> 315346
A11: Cumulative Capital Available | B11: =B10 -> 9844 | C11: =B11+C10 -> 19144 | D11: =C11+D10 -> 35030 | E11: =D11+E10 -> 47578.191 | F11: =E11+F10 -> 67027.874 | G11: =F11+G10 -> 123899.14 | H11: =G11+H10 -> 149422.54 | I11: =H11+I10 -> 166474.56 | J11: =I11+J10 -> 219461.42 | ... M11: =L11+M10 -> 315346
A12: Raise Target (from Dashboard) | B12: =Dashboard!B26 -> 500000 | O12: SAFE + RBF + CDFI total target
A13: % of Raise Closed | B13: =IF(B12>0,(B6+B7+B8)/B12,0) -> 0 | C13: =IF($B$12>0,SUM($B$6:C6,$B$7:C7,$B$8:C8)/$B$12,0) -> 0 | D13: =IF($B$12>0,SUM($B$6:D6,$B$7:D7,$B$8:D8)/$B$12,0) -> 0 | E13: =IF($B$12>0,SUM($B$6:E6,$B$7:E7,$B$8:E8)/$B$12,0) -> 0 | F13: =IF($B$12>0,SUM($B$6:F6,$B$7:F7,$B$8:F8)/$B$12,0) -> 0 | G13: =IF($B$12>0,SUM($B$6:G6,$B$7:G7,$B$8:G8)/$B$12,0) -> 0 | H13: =IF($B$12>0,SUM($B$6:H6,$B$7:H7,$B$8:H8)/$B$12,0) -> 0 | I13: =IF($B$12>0,SUM($B$6:I6,$B$7:I7,$B$8:I8)/$B$12,0) -> 0 | J13: =IF($B$12>0,SUM($B$6:J6,$B$7:J7,$B$8:J8)/$B$12,0) -> 0 | ... M13: =IF($B$12>0,SUM($B$6:M6,$B$7:M7,$B$8:M8)/$B$12,0) -> 0
A15: PLANNED DEPLOYMENTS
A16: Personnel | B16: =SUM(B17:B20) -> 0 | C16: =SUM(C17:C20) -> 0 | D16: =SUM(D17:D20) -> 0 | E16: =SUM(E17:E20) -> 0 | F16: =SUM(F17:F20) -> 0 | G16: =SUM(G17:G20) -> 0 | H16: =SUM(H17:H20) -> 0 | I16: =SUM(I17:I20) -> 0 | ... M16: =SUM(M17:M20) -> 0 | N16: =SUM(B16:M16) -> 0 | O16: Founder salary, eng lead, sales hire
A17: Founder / CEO Salary | B17: 0 | C17: 0 | D17: 0 | E17: 0 | F17: 0 | G17: 0 | H17: 0 | I17: 0 | J17: 0 | K17: 0 | L17: 0 | M17: 0 | N17: =SUM(B17:M17) -> 0 | O17: Starts when raise closes
A18: Engineering Lead | B18: 0 | C18: 0 | D18: 0 | E18: 0 | F18: 0 | G18: 0 | H18: 0 | I18: 0 | J18: 0 | K18: 0 | L18: 0 | M18: 0 | N18: =SUM(B18:M18) -> 0 | O18: Hire when ~$150K raised
A19: Sales / BD Lead | B19: 0 | C19: 0 | D19: 0 | E19: 0 | F19: 0 | G19: 0 | H19: 0 | I19: 0 | J19: 0 | K19: 0 | L19: 0 | M19: 0 | N19: =SUM(B19:M19) -> 0 | O19: Hire when ~$250K raised
A20: Contract Labor | B20: 0 | C20: 0 | D20: 0 | E20: 0 | F20: 0 | G20: 0 | H20: 0 | I20: 0 | J20: 0 | K20: 0 | L20: 0 | M20: 0 | N20: =SUM(B20:M20) -> 0 | O20: Ongoing design/dev contractors
A21: Technology & Platform | B21: =SUM(B22:B23) -> 0 | C21: =SUM(C22:C23) -> 0 | D21: =SUM(D22:D23) -> 0 | E21: =SUM(E22:E23) -> 0 | F21: =SUM(F22:F23) -> 0 | G21: =SUM(G22:G23) -> 0 | H21: =SUM(H22:H23) -> 0 | I21: =SUM(I22:I23) -> 0 | ... M21: =SUM(M22:M23) -> 0 | N21: =SUM(B21:M21) -> 0 | O21: Platform rebuild + infrastructure
A22: Platform Rebuild (v2) | B22: 0 | C22: 0 | D22: 0 | E22: 0 | F22: 0 | G22: 0 | H22: 0 | I22: 0 | J22: 0 | K22: 0 | L22: 0 | M22: 0 | N22: =SUM(B22:M22) -> 0 | O22: Major investment in Q2-Q3
A23: Software & Subscriptions | B23: 0 | C23: 0 | D23: 0 | E23: 0 | F23: 0 | G23: 0 | H23: 0 | I23: 0 | J23: 0 | K23: 0 | L23: 0 | M23: 0 | N23: =SUM(B23:M23) -> 0 | O23: AI tools, APIs, hosting
A24: Marketing & Growth | B24: =SUM(B25:B27) -> 0 | C24: =SUM(C25:C27) -> 0 | D24: =SUM(D25:D27) -> 0 | E24: =SUM(E25:E27) -> 0 | F24: =SUM(F25:F27) -> 0 | G24: =SUM(G25:G27) -> 0 | H24: =SUM(H25:H27) -> 0 | I24: =SUM(I25:I27) -> 0 | ... M24: =SUM(M25:M27) -> 0 | N24: =SUM(B24:M24) -> 0 | O24: Brand launch + paid campaigns
A25: Brand Campaign Launch | B25: 0 | C25: 0 | D25: 0 | E25: 0 | F25: 0 | G25: 0 | H25: 0 | I25: 0 | J25: 0 | K25: 0 | L25: 0 | M25: 0 | N25: =SUM(B25:M25) -> 0 | O25: Major push when platform ships
A26: Paid Digital Ads | B26: 0 | C26: 0 | D26: 0 | E26: 0 | F26: 0 | G26: 0 | H26: 0 | I26: 0 | J26: 0 | K26: 0 | L26: 0 | M26: 0 | N26: =SUM(B26:M26) -> 0 | O26: Ramp up through year
A27: Conferences & Speaking | B27: 0 | C27: 0 | D27: 0 | E27: 0 | F27: 0 | G27: 0 | H27: 0 | I27: 0 | J27: 0 | K27: 0 | L27: 0 | M27: 0 | N27: =SUM(B27:M27) -> 0 | O27: NY Tech Week, FxF events
A28: Events & Community | B28: 0 | C28: 0 | D28: 0 | E28: 0 | F28: 0 | G28: 0 | H28: 0 | I28: 0 | J28: 0 | K28: 0 | L28: 0 | M28: 0 | N28: =SUM(B28:M28) -> 0 | O28: Event production + programs
A29: Compliance & Legal | B29: 0 | C29: 0 | D29: 0 | E29: 0 | F29: 0 | G29: 0 | H29: 0 | I29: 0 | J29: 0 | K29: 0 | L29: 0 | M29: 0 | N29: =SUM(B29:M29) -> 0 | O29: Reg advisory, legal, accounting
A30: Operations & Admin | B30: 0 | C30: 0 | D30: 0 | E30: 0 | F30: 0 | G30: 0 | H30: 0 | I30: 0 | J30: 0 | K30: 0 | L30: 0 | M30: 0 | N30: =SUM(B30:M30) -> 0 | O30: Travel, insurance, overhead
A31: Total Planned Deployments | B31: =B16+B21+B24+B28+B29+B30 -> 0 | C31: =C16+C21+C24+C28+C29+C30 -> 0 | D31: =D16+D21+D24+D28+D29+D30 -> 0 | E31: =E16+E21+E24+E28+E29+E30 -> 0 | F31: =F16+F21+F24+F28+F29+F30 -> 0 | G31: =G16+G21+G24+G28+G29+G30 -> 0 | H31: =H16+H21+H24+H28+H29+H30 -> 0 | I31: =I16+I21+I24+I28+I29+I30 -> 0 | ... M31: =M16+M21+M24+M28+M29+M30 -> 0 | N31: =SUM(B31:M31) -> 0
A33: CASH POSITION
A34: Starting Cash | B34: 5000 | C34: =B37 -> 14844 | D34: =C37 -> 24144 | E34: =D37 -> 40030 | F34: =E37 -> 52578.191 | G34: =F37 -> 72027.874 | H34: =G37 -> 128899.14 | I34: =H37 -> 154422.54 | J34: =I37 -> 171474.56 | ... M34: =L37 -> 294931.71 | O34: Cash on hand before raise begins
A35: + New Capital In | B35: =B10 -> 9844 | C35: =C10 -> 9300 | D35: =D10 -> 15886 | E35: =E10 -> 12548.191 | F35: =F10 -> 19449.683 | G35: =G10 -> 56871.266 | H35: =H10 -> 25523.398 | I35: =I10 -> 17052.027 | ... M35: =M10 -> 25414.288
A36: - Planned Deployments | B36: =-B31 -> 0 | C36: =-C31 -> 0 | D36: =-D31 -> 0 | E36: =-E31 -> 0 | F36: =-F31 -> 0 | G36: =-G31 -> 0 | H36: =-H31 -> 0 | I36: =-I31 -> 0 | ... M36: =-M31 -> 0
A37: Ending Cash Balance | B37: =B34+B35+B36 -> 14844 | C37: =C34+C35+C36 -> 24144 | D37: =D34+D35+D36 -> 40030 | E37: =E34+E35+E36 -> 52578.191 | F37: =F34+F35+F36 -> 72027.874 | G37: =G34+G35+G36 -> 128899.14 | H37: =H34+H35+H36 -> 154422.54 | I37: =I34+I35+I36 -> 171474.56 | ... M37: =M34+M35+M36 -> 320346
A38: Months of Runway | B38: =IF(C31>0,B37/C31,0) -> 0 | C38: =IF(D31>0,C37/D31,0) -> 0 | D38: =IF(E31>0,D37/E31,0) -> 0 | E38: =IF(F31>0,E37/F31,0) -> 0 | F38: =IF(G31>0,F37/G31,0) -> 0 | G38: =IF(H31>0,G37/H31,0) -> 0 | H38: =IF(I31>0,H37/I31,0) -> 0 | I38: =IF(J31>0,I37/J31,0) -> 0 | ... L38: =IF(M31>0,L37/M31,0) -> 0 | O38: Ending cash ÷ next month's planned spend
A40: DEPLOYMENT MILESTONES
A41: When This Closes... | C41: ...You Can Deploy
A42: $50K raised | B42: $50K | C42: Start founder salary ($5K/mo), contract labor, basic software
A43: $100K raised | B43: $100K | C43: Add platform infrastructure spend, begin brand campaign planning
A44: $150K raised | B44: $150K | C44: Hire engineering lead, begin platform v2 rebuild
A45: $200K raised | B45: $200K | C45: Launch paid digital ads, ramp conference/speaking budget
A46: $250K raised | B46: $250K | C46: Hire sales/BD lead, expand event production budget
A47: $350K raised | B47: $350K | C47: Full marketing ramp, community grants, compliance/legal
A48: $500K raised (full) | B48: $500K | C48: All systems go — full team, full marketing, full events calendar
A50: RAISE vs TARGET
A51: SAFE Target | B51: =Dashboard!B23 -> 250000 | C51: SAFE Raised to Date | D51: =N6 -> 0 | E51: Remaining | F51: =B51-D51 -> 250000
A52: RBF Target | B52: =Dashboard!B24 -> 150000 | C52: RBF Raised to Date | D52: =N7 -> 0 | E52: Remaining | F52: =B52-D52 -> 150000
A53: CDFI Target | B53: =Dashboard!B25 -> 100000 | C53: CDFI Raised to Date | D53: =N8 -> 0 | E53: Remaining | F53: =B53-D53 -> 100000
A54: Total Raise | B54: =B51+B52+B53 -> 500000 | C54: Total Raised | D54: =D51+D52+D53 -> 0 | E54: Remaining | F54: =F51+F52+F53 -> 500000

Sheet Historical P&L
A1: HISTORICAL PROFIT & LOSS
A2: IBC Real Estate and Advising INC (dba Sengo)
B4: 2024 (Actual) | C4: 2025 (Actual) | D4: YoY Growth | E4: Source
A5: REVENUE
A6: Events Income | B6: 29832 | C6: 44344 | D6: =IF(B6>0,(C6-B6)/B6,IF(C6>0,1,0)) -> 0.4864575 | E6: Source: P&L ($3,250 reclassified to B2B/Sponsorships)
A7: Sales & Client Reimbursements | B7: 2520 | C7: 26296 | D7: =IF(B7>0,(C7-B7)/B7,IF(C7>0,1,0)) -> 9.4349206 | E7: Source: P&L
A8: Services & Consulting | B8: 20667 | C8: 48405 | D8: =IF(B8>0,(C8-B8)/B8,IF(C8>0,1,0)) -> 1.3421396 | E8: Source: P&L
A9: SaaS Subscriptions | B9: 0 | C9: 18230 | D9: =IF(B9>0,(C9-B9)/B9,IF(C9>0,1,0)) -> 1 | E9: Source: P&L
A10: Coaching | B10: 0 | C10: 2000 | D10: =IF(B10>0,(C10-B10)/B10,IF(C10>0,1,0)) -> 1 | E10: Source: P&L
A11: B2B / Sponsorships | B11: 0 | C11: 18250 | D11: =IF(B11>0,(C11-B11)/B11,IF(C11>0,1,0)) -> 1 | E11: Source: P&L (partner deployments + sponsorships reclassified)
A12: Grants | B12: 0 | C12: 37156 | D12: Source: P&L (BGV Fellowship, W.E. Build; reduced $17.5K) | E12: Source: P&L (Square, BGV Fellowship, W.E. Build)
A13: Total Revenue | B13: =SUM(B6:B12) -> 53019 | C13: =SUM(C6:C12) -> 194681 | D13: =IF(B13>0,(C13-B13)/B13,0) -> 2.6719101
A15: COST OF GOODS SOLD
A16: COGS | B16: 432 | C16: 19684 | E16: Source: P&L
A18: PROFITABILITY
A19: Gross Profit | B19: =B13-B16 -> 52587 | C19: =C13-C16 -> 174997
A20: Gross Margin | B20: =IF(B13>0,B19/B13,0) -> 0.99185198 | C20: =IF(C13>0,C19/C13,0) -> 0.89889101
A22: Total Operating Expenses | B22: 53967 | C22: 100299 | E22: Source: P&L
A23: OpEx % of Revenue | B23: =IF(B13>0,B22/B13,0) -> 1.0178804 | C23: =IF(C13>0,C22/C13,0) -> 0.51519666
A25: Net Operating Income | B25: =B19-B22 -> -1380 | C25: =C19-C22 -> 74698
A26: Other Expenses | B26: 101 | C26: 233
A28: BOTTOM LINE
A29: Net Income | B29: =B25-B26 -> -1481 | C29: =C25-C26 -> 74465 | D29: =IF(ABS(B29)>0,(C29-B29)/ABS(B29),0) -> 51.280216
A30: Net Margin | B30: =IF(B13>0,B29/B13,0) -> -0.027933382 | C30: =IF(C13>0,C29/C13,0) -> 0.38249752

Sheet 2026 Monthly P&L
A1: 2026 MONTHLY P&L
A2: Actuals (blue) vs Budget (yellow) — updated March 2026
B4: Jan | C4: Feb | D4: Mar | E4: Apr | F4: May | G4: Jun | H4: Jul | I4: Aug | J4: Sep | K4: Oct | L4: Nov | M4: Dec | N4: YTD Actual | O4: 2026 Budget
A5: REVENUE
A6: SaaS Subscriptions | B6: 1886 | C6: 1886 | D6: 1886 | E6: =(Assumptions!C7-SUM($B6:$D6))*2200/39900 -> 2960.2406 | F6: =(Assumptions!C7-SUM($B6:$D6))*2500/39900 -> 3363.9098 | G6: =(Assumptions!C7-SUM($B6:$D6))*3000/39900 -> 4036.6917 | H6: =(Assumptions!C7-SUM($B6:$D6))*3500/39900 -> 4709.4737 | I6: =(Assumptions!C7-SUM($B6:$D6))*4200/39900 -> 5651.3684 | J6: =(Assumptions!C7-SUM($B6:$D6))*5000/39900 -> 6727.8195 | K6: =(Assumptions!C7-SUM($B6:$D6))*5800/39900 -> 7804.2707 | L6: =(Assumptions!C7-SUM($B6:$D6))*6500/39900 -> 8746.1654 | M6: =(Assumptions!C7-SUM($B6:$D6))*7200/39900 -> 9688.0602 | N6: =SUM(B6:D6) -> 5658 | O6: =SUM(B6:M6) -> 59346
A7: Coaching Programs | B7: 4000 | C7: 3500 | D7: 14000 | E7: =(Assumptions!C17-SUM($B7:$D7))*3500/49000 -> 4107.1429 | F7: =(Assumptions!C17-SUM($B7:$D7))*3500/49000 -> 4107.1429 | G7: =(Assumptions!C17-SUM($B7:$D7))*4500/49000 -> 5280.6122 | H7: =(Assumptions!C17-SUM($B7:$D7))*5000/49000 -> 5867.3469 | I7: =(Assumptions!C17-SUM($B7:$D7))*5500/49000 -> 6454.0816 | J7: =(Assumptions!C17-SUM($B7:$D7))*6000/49000 -> 7040.8163 | K7: =(Assumptions!C17-SUM($B7:$D7))*6500/49000 -> 7627.551 | L7: =(Assumptions!C17-SUM($B7:$D7))*7000/49000 -> 8214.2857 | M7: =(Assumptions!C17-SUM($B7:$D7))*7500/49000 -> 8801.0204 | N7: =SUM(B7:D7) -> 21500 | O7: =SUM(B7:M7) -> 79000
A8: Events & Sales | B8: 3958 | C8: 3914 | D8: 0 | E8: 0 | F8: 0 | G8: =(Assumptions!C25-SUM($B8:$D8))*28000/52000 -> 42607.385 | H8: 0 | I8: 0 | J8: =(Assumptions!C25-SUM($B8:$D8))*14000/52000 -> 21303.692 | K8: 0 | L8: =(Assumptions!C25-SUM($B8:$D8))*10000/52000 -> 15216.923 | M8: 0 | N8: =SUM(B8:D8) -> 7872 | O8: =SUM(B8:M8) -> 87000
A9: B2B / Sponsorships | B9: 0 | C9: 0 | D9: 0 | E9: =(Assumptions!C34-SUM($B9:$D9))*5540/50540 -> 5480.8073 | F9: =(Assumptions!C34-SUM($B9:$D9))*2000/50540 -> 1978.6308 | G9: =(Assumptions!C34-SUM($B9:$D9))*5000/50540 -> 4946.577 | H9: =(Assumptions!C34-SUM($B9:$D9))*5000/50540 -> 4946.577 | I9: =(Assumptions!C34-SUM($B9:$D9))*5000/50540 -> 4946.577 | J9: =(Assumptions!C34-SUM($B9:$D9))*8000/50540 -> 7914.5231 | K9: =(Assumptions!C34-SUM($B9:$D9))*5000/50540 -> 4946.577 | L9: =(Assumptions!C34-SUM($B9:$D9))*8000/50540 -> 7914.5231 | M9: =(Assumptions!C34-SUM($B9:$D9))*7000/50540 -> 6925.2078 | N9: =SUM(B9:D9) -> 0 | O9: =SUM(B9:M9) -> 50000
A10: Grants | B10: 0 | C10: 0 | D10: 0 | E10: 0 | F10: =(Assumptions!C40-SUM($B10:$D10))*10000/40000 -> 10000 | G10: 0 | H10: =(Assumptions!C40-SUM($B10:$D10))*10000/40000 -> 10000 | I10: 0 | J10: =(Assumptions!C40-SUM($B10:$D10))*10000/40000 -> 10000 | K10: 0 | L10: =(Assumptions!C40-SUM($B10:$D10))*10000/40000 -> 10000 | M10: 0 | N10: =SUM(B10:D10) -> 0 | O10: =SUM(B10:M10) -> 40000
A11: Total Revenue | B11: 9844 | C11: 9300 | D11: =SUM(D6:D10) -> 15886 | E11: =SUM(E6:E10) -> 12548.191 | F11: =SUM(F6:F10) -> 19449.683 | G11: =SUM(G6:G10) -> 56871.266 | H11: =SUM(H6:H10) -> 25523.398 | I11: =SUM(I6:I10) -> 17052.027 | J11: =SUM(J6:J10) -> 52986.851 | K11: =SUM(K6:K10) -> 20378.399 | ... M11: =SUM(M6:M10) -> 25414.288 | N11: =SUM(B11:D11) -> 35030 | O11: =SUM(B11:M11) -> 315346
A13: COGS (~10%) | B13: =-ABS(B11*0.1) -> -984.4 | C13: =-ABS(C11*0.1) -> -930 | D13: =-ABS(D11*0.1) -> -1588.6 | E13: =-ABS(E11*0.1) -> -1254.8191 | F13: =-ABS(F11*0.1) -> -1944.9683 | G13: =-ABS(G11*0.1) -> -5687.1266 | H13: =-ABS(H11*0.1) -> -2552.3398 | I13: =-ABS(I11*0.1) -> -1705.2027 | ... M13: =-ABS(M11*0.1) -> -2541.4288 | N13: =SUM(B13:D13) -> -3503 | O13: =SUM(B13:M13) -> -31534.6
A14: Gross Profit | B14: =B11+B13 -> 8859.6 | C14: =C11+C13 -> 8370 | D14: =D11+D13 -> 14297.4 | E14: =E11+E13 -> 11293.372 | F14: =F11+F13 -> 17504.715 | G14: =G11+G13 -> 51184.139 | H14: =H11+H13 -> 22971.058 | I14: =I11+I13 -> 15346.824 | ... O14: =O11+O13 -> 283811.4
A16: OPERATING EXPENSES
A17: Personnel | B17: 1135 | C17: 349 | D17: 1160 | E17: =(Assumptions!C47-SUM($B17:$D17))*1160/142575 -> 1442.9806 | F17: =(Assumptions!C47-SUM($B17:$D17))*8000/142575 -> 9951.5904 | G17: =(Assumptions!C47-SUM($B17:$D17))*14417/142575 -> 17934.01 | H17: =(Assumptions!C47-SUM($B17:$D17))*19833/142575 -> 24671.237 | I17: =(Assumptions!C47-SUM($B17:$D17))*19833/142575 -> 24671.237 | J17: =(Assumptions!C47-SUM($B17:$D17))*19833/142575 -> 24671.237 | K17: =(Assumptions!C47-SUM($B17:$D17))*19833/142575 -> 24671.237 | L17: =(Assumptions!C47-SUM($B17:$D17))*19833/142575 -> 24671.237 | M17: =(Assumptions!C47-SUM($B17:$D17))*19833/142575 -> 24671.237 | N17: =SUM(B17:D17) -> 2644 | O17: =SUM(B17:M17) -> 180000
A18: Technology & Platform | B18: 80 | C18: 84 | D18: 100 | E18: =(Assumptions!C54-SUM($B18:$D18))*3500/61000 -> 4861.9016 | F18: =(Assumptions!C54-SUM($B18:$D18))*5000/61000 -> 6945.5738 | G18: =(Assumptions!C54-SUM($B18:$D18))*7500/61000 -> 10418.361 | H18: =(Assumptions!C54-SUM($B18:$D18))*7500/61000 -> 10418.361 | I18: =(Assumptions!C54-SUM($B18:$D18))*7500/61000 -> 10418.361 | J18: =(Assumptions!C54-SUM($B18:$D18))*7500/61000 -> 10418.361 | K18: =(Assumptions!C54-SUM($B18:$D18))*7500/61000 -> 10418.361 | L18: =(Assumptions!C54-SUM($B18:$D18))*7500/61000 -> 10418.361 | M18: =(Assumptions!C54-SUM($B18:$D18))*7500/61000 -> 10418.361 | N18: =SUM(B18:D18) -> 264 | O18: =SUM(B18:M18) -> 85000
A19: Marketing & Growth | B19: 0 | C19: 0 | D19: 500 | E19: =(Assumptions!C57-SUM($B19:$D19))*3000/92000 -> 3570.6522 | F19: =(Assumptions!C57-SUM($B19:$D19))*5000/92000 -> 5951.087 | G19: =(Assumptions!C57-SUM($B19:$D19))*8000/92000 -> 9521.7391 | H19: =(Assumptions!C57-SUM($B19:$D19))*10000/92000 -> 11902.174 | I19: =(Assumptions!C57-SUM($B19:$D19))*12000/92000 -> 14282.609 | J19: =(Assumptions!C57-SUM($B19:$D19))*12000/92000 -> 14282.609 | K19: =(Assumptions!C57-SUM($B19:$D19))*14000/92000 -> 16663.043 | L19: =(Assumptions!C57-SUM($B19:$D19))*14000/92000 -> 16663.043 | M19: =(Assumptions!C57-SUM($B19:$D19))*14000/92000 -> 16663.043 | N19: =SUM(B19:D19) -> 500 | O19: =SUM(B19:M19) -> 110000
A20: Events & Community | B20: 2844 | C20: 7611 | D20: 2000 | E20: =(Assumptions!C63-SUM($B20:$D20))*2000/38000 -> 2502.3684 | F20: =(Assumptions!C63-SUM($B20:$D20))*3000/38000 -> 3753.5526 | G20: =(Assumptions!C63-SUM($B20:$D20))*4000/38000 -> 5004.7368 | H20: =(Assumptions!C63-SUM($B20:$D20))*4000/38000 -> 5004.7368 | I20: =(Assumptions!C63-SUM($B20:$D20))*5000/38000 -> 6255.9211 | J20: =(Assumptions!C63-SUM($B20:$D20))*5000/38000 -> 6255.9211 | K20: =(Assumptions!C63-SUM($B20:$D20))*5000/38000 -> 6255.9211 | L20: =(Assumptions!C63-SUM($B20:$D20))*5000/38000 -> 6255.9211 | M20: =(Assumptions!C63-SUM($B20:$D20))*5000/38000 -> 6255.9211 | N20: =SUM(B20:D20) -> 12455 | O20: =SUM(B20:M20) -> 60000
A21: Compliance & Legal | B21: 0 | C21: 0 | D21: 50 | E21: =(Assumptions!C66-SUM($B21:$D21))*2000/40000 -> 2247.5 | F21: =(Assumptions!C66-SUM($B21:$D21))*3000/40000 -> 3371.25 | G21: =(Assumptions!C66-SUM($B21:$D21))*5000/40000 -> 5618.75 | H21: =(Assumptions!C66-SUM($B21:$D21))*5000/40000 -> 5618.75 | I21: =(Assumptions!C66-SUM($B21:$D21))*5000/40000 -> 5618.75 | J21: =(Assumptions!C66-SUM($B21:$D21))*5000/40000 -> 5618.75 | K21: =(Assumptions!C66-SUM($B21:$D21))*5000/40000 -> 5618.75 | L21: =(Assumptions!C66-SUM($B21:$D21))*5000/40000 -> 5618.75 | M21: =(Assumptions!C66-SUM($B21:$D21))*5000/40000 -> 5618.75 | N21: =SUM(B21:D21) -> 50 | O21: =SUM(B21:M21) -> 45000
A22: Operations & Admin | B22: 540 | C22: 451 | D22: 200 | E22: =(Assumptions!C67-SUM($B22:$D22))*500/14500 -> 579.62069 | F22: =(Assumptions!C67-SUM($B22:$D22))*1000/14500 -> 1159.2414 | G22: =(Assumptions!C67-SUM($B22:$D22))*1500/14500 -> 1738.8621 | H22: =(Assumptions!C67-SUM($B22:$D22))*1500/14500 -> 1738.8621 | I22: =(Assumptions!C67-SUM($B22:$D22))*2000/14500 -> 2318.4828 | J22: =(Assumptions!C67-SUM($B22:$D22))*2000/14500 -> 2318.4828 | K22: =(Assumptions!C67-SUM($B22:$D22))*2000/14500 -> 2318.4828 | L22: =(Assumptions!C67-SUM($B22:$D22))*2000/14500 -> 2318.4828 | M22: =(Assumptions!C67-SUM($B22:$D22))*2000/14500 -> 2318.4828 | N22: =SUM(B22:D22) -> 1191 | O22: =SUM(B22:M22) -> 18000
A25: Total Operating Expenses | B25: 4599 | C25: 8495 | D25: =SUM(D17:D22) -> 4010 | E25: =SUM(E17:E22) -> 15205.024 | F25: =SUM(F17:F22) -> 31132.295 | G25: =SUM(G17:G22) -> 50236.459 | H25: =SUM(H17:H22) -> 59354.12 | I25: =SUM(I17:I22) -> 63565.36 | J25: =SUM(J17:J22) -> 63565.36 | K25: =SUM(K17:K22) -> 65945.794 | ... M25: =SUM(M17:M22) -> 65945.794 | N25: =SUM(B25:D25) -> 17104 | O25: =SUM(B25:M25) -> 498000
A27: PROFITABILITY
A28: Net Operating Income | B28: =B14-B25 -> 4260.6 | C28: =C14-C25 -> -125 | D28: =D14-D25 -> 10287.4 | E28: =E14-E25 -> -3911.6519 | F28: =F14-F25 -> -13627.58 | G28: =G14-G25 -> 947.68047 | H28: =H14-H25 -> -36383.062 | I28: =I14-I25 -> -48218.535 | ... O28: =O14-O25 -> -214188.6
A29: Operating Margin | B29: =IF(B11>0,B28/B11,0) -> 0.43281187 | C29: =IF(C11>0,C28/C11,0) -> -0.01344086 | D29: =IF(D11>0,D28/D11,0) -> 0.64757648 | E29: =IF(E11>0,E28/E11,0) -> -0.31173035 | F29: =IF(F11>0,F28/F11,0) -> -0.70065819 | G29: =IF(G11>0,G28/G11,0) -> 0.016663608 | H29: =IF(H11>0,H28/H11,0) -> -1.4254788 | I29: =IF(I11>0,I28/I11,0) -> -2.8277304 | ... O29: =IF(O11>0,O28/O11,0) -> -0.67921775
A31: CASH FLOW
A32: Pre-Seed Investment | B32: 0 | C32: 0 | D32: 0 | E32: 0 | F32: 250000 | G32: 250000 | H32: 0 | I32: 0 | J32: 0 | K32: 0 | L32: 0 | M32: 0 | N32: =SUM(B32:D32) -> 0 | O32: =SUM(B32:M32) -> 500000
A33: Monthly Cash Flow | B33: =B28+B32 -> 4260.6 | C33: =C28+C32 -> -125 | D33: =D28+D32 -> 10287.4 | E33: =E28+E32 -> -3911.6519 | F33: =F28+F32 -> 236372.42 | G33: =G28+G32 -> 250947.68 | H33: =H28+H32 -> -36383.062 | I33: =I28+I32 -> -48218.535 | ... O33: =O28+O32 -> 285811.4
A34: Cumulative Cash Position | B34: =5000+B33 -> 9260.6 | C34: =B34+C33 -> 9135.6 | D34: =C34+D33 -> 19423 | E34: =D34+E33 -> 15511.348 | F34: =E34+F33 -> 251883.77 | G34: =F34+G33 -> 502831.45 | H34: =G34+H33 -> 466448.39 | I34: =H34+I33 -> 418229.85 | J34: =I34+J33 -> 402352.66 | ... M34: =L34+M33 -> 290811.4 | N34: =D34 -> 19423 | O34: =M34 -> 290811.4
A36: NOTES
A37: Blue = actuals (QB P&L totals). Yellow = budget months are formula-driven from Assumptions sheet.
A38: Jan/Feb Total Revenue & Total OpEx match QuickBooks P&L exactly.
A39: Mar coaching includes $10K deferred payout. Apr B2B includes $5,540 confirmed partnership.
A40: FxF NYC vendor payments collected Dec/Jan; shown in Events when received per QB.
A41: Personnel ramps post-raise: Eng Lead (Q2), Sales/BD Lead (Q3).
A43: ACTUALS vs. PROJECTIONS
A44: Jan actual revenue of $9,844 exceeded monthly run-rate target ($27.4K/12 ann. avg is misleading
A45: — given back-loaded revenue ramp). Jan is a strong baseline month: 5 active revenue streams.
A46: Jan OpEx of $4,599 (pre-hire) yielded ~$4,261 net operating income — rare for a pre-seed company.
A47: Feb revenue of $9,300 showed consistency with Jan, maintaining $1,886 MRR base.
A48: Feb OpEx of $8,495 included FxF NYC event costs — net income near breakeven (~-$125).
... A50: Key takeaway: Revenue is real, recurring, and diversified. OpEx is disciplined. Pre-raise burn is minimal.

Sheet Projections
A1: 3-YEAR PROJECTED P&L
A2: All projections driven by Assumptions sheet
B4: 2025 (Actual) | C4: 2026 (Proj) | D4: 2027 (Proj) | E4: 2028 (Proj)
A5: REVENUE
A6: SaaS Subscriptions | B6: =Assumptions!B7 -> 18230 | C6: =Assumptions!C7 -> 59346 | D6: =Assumptions!D7 -> 205530 | E6: =Assumptions!E7 -> 502500
A7: Legacy ($7/mo) | B7: =Assumptions!B9 -> 1100 | C7: =Assumptions!C9 -> 1176 | D7: =Assumptions!D9 -> 630 | E7: =Assumptions!E9 -> 0
A8: Investor ($10/mo) | B8: =Assumptions!B11 -> 400 | C8: =Assumptions!C11 -> 2640 | D8: =Assumptions!D11 -> 14400 | E8: =Assumptions!E11 -> 42000
A9: Founder ($15/mo) | B9: =Assumptions!B13 -> 15830 | C9: =Assumptions!C13 -> 46080 | D9: =Assumptions!D13 -> 144000 | E9: =Assumptions!E13 -> 333000
A10: All Access ($25/mo) | B10: =Assumptions!B15 -> 900 | C10: =Assumptions!C15 -> 9450 | D10: =Assumptions!D15 -> 46500 | E10: =Assumptions!E15 -> 127500
A12: Coaching | B12: =Assumptions!B17 -> 2000 | C12: =Assumptions!C17 -> 79000 | D12: =Assumptions!D17 -> 177000 | E12: =Assumptions!E17 -> 420000
A13: Legacy ($500/mo) | B13: =Assumptions!B19 -> 1000 | C13: =Assumptions!C19 -> 9000 | D13: =Assumptions!D19 -> 3000 | E13: =Assumptions!E19 -> 0
A14: Foundation ($1,000/mo) | B14: =Assumptions!B21 -> 500 | C14: =Assumptions!C21 -> 24000 | D14: =Assumptions!D21 -> 66000 | E14: =Assumptions!E21 -> 156000
A15: Accelerator ($2,000/mo) | B15: =Assumptions!B23 -> 500 | C15: =Assumptions!C23 -> 36000 | D15: =Assumptions!D23 -> 108000 | E15: =Assumptions!E23 -> 264000
A17: Events & Sales | B17: =Assumptions!B25 -> 70640 | C17: =Assumptions!C25 -> 87000 | D17: =Assumptions!D25 -> 140000 | E17: =Assumptions!E25 -> 212000
A18: FxF NYC (Feb) | B18: =Assumptions!B26 -> 0 | C18: =Assumptions!C26 -> 17000 | D18: =Assumptions!D26 -> 25000 | E18: =Assumptions!E26 -> 35000
A19: NY Tech Week (June) | B19: =Assumptions!B27 -> 0 | C19: =Assumptions!C27 -> 5000 | D19: =Assumptions!D27 -> 8000 | E19: =Assumptions!E27 -> 12000
A20: FxF LA (June) | B20: =Assumptions!B28 -> 0 | C20: =Assumptions!C28 -> 10000 | D20: =Assumptions!D28 -> 16000 | E20: =Assumptions!E28 -> 24000
A21: FxF NYC (Sept) | B21: =Assumptions!B29 -> 0 | C21: =Assumptions!C29 -> 14000 | D21: =Assumptions!D29 -> 22000 | E21: =Assumptions!E29 -> 32000
A22: FxF LA (Nov) | B22: =Assumptions!B30 -> 0 | C22: =Assumptions!C30 -> 10000 | D22: =Assumptions!D30 -> 16000 | E22: =Assumptions!E30 -> 24000
A23: Other In-Person (3 TBD) | B23: =Assumptions!B31 -> 0 | C23: =Assumptions!C31 -> 21000 | D23: =Assumptions!D31 -> 33000 | E23: =Assumptions!E31 -> 50000
A24: Virtual Events | B24: =Assumptions!B32 -> 0 | C24: =Assumptions!C32 -> 10000 | D24: =Assumptions!D32 -> 20000 | E24: =Assumptions!E32 -> 35000
A26: B2B / Sponsorships | B26: =Assumptions!B34 -> 18250 | C26: =Assumptions!C34 -> 50000 | D26: =Assumptions!D34 -> 255000 | E26: =Assumptions!E34 -> 635000
A27: Event Partners ($10K-$25K) | B27: =Assumptions!B35 -> 0 | C27: =Assumptions!C35 -> 30000 | D27: =Assumptions!D35 -> 100000 | E27: =Assumptions!E35 -> 200000
A28: Media Partners ($2K-$5K) | B28: =Assumptions!B36 -> 0 | C28: =Assumptions!C36 -> 10000 | D28: =Assumptions!D36 -> 30000 | E28: =Assumptions!E36 -> 60000
... A33: Services & Consulting | B33: =Assumptions!B41 -> 48405 | C33: =Assumptions!C41 -> 0 | D33: =Assumptions!D41 -> 0 | E33: =Assumptions!E41 -> 0
A34: Total Revenue | B34: =B6+B12+B17+B26+B32+B33 -> 194681 | C34: =C6+C12+C17+C26+C32+C33 -> 315346 | D34: =D6+D12+D17+D26+D32+D33 -> 797530 | E34: =E6+E12+E17+E26+E32+E33 -> 1769500
A35: COGS | B35: =-ABS(B34*Assumptions!B44) -> -18105.333 | C35: =-ABS(C34*Assumptions!C44) -> -31534.6 | D35: =-ABS(D34*Assumptions!D44) -> -79753 | E35: =-ABS(E34*Assumptions!E44) -> -159255
A36: Gross Profit | B36: =B34+B35 -> 176575.67 | C36: =C34+C35 -> 283811.4 | D36: =D34+D35 -> 717777 | E36: =E34+E35 -> 1610245
A37: Gross Margin | B37: =IF(B34>0,B36/B34,0) -> 0.907 | C37: =IF(C34>0,C36/C34,0) -> 0.9 | D37: =IF(D34>0,D36/D34,0) -> 0.9 | E37: =IF(E34>0,E36/E34,0) -> 0.91
A38: Operating Expenses | B38: =-ABS(Assumptions!B68) -> -96000 | C38: =-ABS(Assumptions!C68) -> -498000 | D38: =-ABS(Assumptions!D68) -> -778000 | E38: =-ABS(Assumptions!E68) -> -1020000
A39: Operating Income | B39: =B36+B38 -> 80575.667 | C39: =C36+C38 -> -214188.6 | D39: =D36+D38 -> -60223 | E39: =E36+E38 -> 590245
A40: Operating Margin | B40: =IF(B34>0,B39/B34,0) -> 0.41388562 | C40: =IF(C34>0,C39/C34,0) -> -0.67921775 | D40: =IF(D34>0,D39/D34,0) -> -0.075511893 | E40: =IF(E34>0,E39/E34,0) -> 0.33356598
A41: DEBT SERVICE
A42: RBF Revenue Share Payment | B42: 0 | C42: =-IF('Valuation & Exit'!B47>0,MIN('Valuation & Exit'!C45,'Valuation & Exit'!B47),0) -> -15767.3 | D42: =-IF('Valuation & Exit'!C47>0,MIN('Valuation & Exit'!D45,'Valuation & Exit'!C47),0) -> -39876.5 | E42: =-IF('Valuation & Exit'!D47>0,MIN('Valuation & Exit'!E45,'Valuation & Exit'!D47),0) -> -88475 | F42: Revenue x share %, capped at max repayment
A43: CDFI Loan Payment | B43: 0 | C43: =-ABS('Valuation & Exit'!B54) -> -23739.64 | D43: =-ABS('Valuation & Exit'!B54) -> -23739.64 | E43: =-ABS('Valuation & Exit'!B54) -> -23739.64 | F43: Fixed annual PMT from CDFI loan
A44: Total Debt Service | B44: =B42+B43 -> 0 | C44: =C42+C43 -> -39506.94 | D44: =D42+D43 -> -63616.14 | E44: =E42+E43 -> -112214.64
A45: Net Income | B45: =B39+B44 -> 80575.667 | C45: =C39+C44 -> -253695.54 | D45: =D39+D44 -> -123839.14 | E45: =E39+E44 -> 478030.36
A46: Net Margin | B46: =IF(B34>0,B45/B34,0) -> 0.41388562 | C46: =IF(C34>0,C45/C34,0) -> -0.80449899 | D46: =IF(D34>0,D45/D34,0) -> -0.15527835 | E46: =IF(E34>0,E45/E34,0) -> 0.27014996
A47: Pre-Seed Investment | B47: =Assumptions!B71 -> 0 | C47: =Assumptions!C71 -> 500000 | D47: =Assumptions!D71 -> 0 | E47: =Assumptions!E71 -> 0
A48: Cash Position (EOY) | B48: =Assumptions!B72+B45+B47 -> 85575.667 | C48: =B48+C45+C47 -> 331880.13 | D48: =C48+D45+D47 -> 208040.99 | E48: =D48+E45+E47 -> 686071.35
A50: KEY METRICS
A51: Total SaaS Subscribers | B51: =Assumptions!B75 -> 132 | C51: =Assumptions!C75 -> 515 | D51: =Assumptions!D75 -> 1650 | E51: =Assumptions!E75 -> 3600
A52: Total Coaching Clients | B52: =Assumptions!B76 -> 4 | C52: =Assumptions!C76 -> 6 | D52: =Assumptions!D76 -> 15 | E52: =Assumptions!E76 -> 33
A53: Email Subscribers | B53: =Assumptions!B77 -> 10000 | C53: =Assumptions!C77 -> 25000 | D53: =Assumptions!D77 -> 60000 | E53: =Assumptions!E77 -> 120000
A55: Revenue per Employee (est.) | B55: =B34/1 -> 194681 | C55: =C34/4 -> 78836.5 | D55: =D34/6 -> 132921.67 | E55: =E34/10 -> 176950
A56: LTV:CAC Ratio | B56: =Assumptions!B82 -> 7.0243056 | C56: =Assumptions!C82 -> 3.0979591 | D56: =Assumptions!D82 -> 6.8445683 | E56: =Assumptions!E82 -> 11.567575

Sheet Bootstrapped
A1: BOOTSTRAPPED SCENARIO
A2: No external funding — organic growth, stay profitable
A3: Compare to Funded Projections tab
B5: 2025 (Actual) | C5: 2026 | D5: 2027 | E5: 2028 | F5: Notes
A6: REVENUE (Organic Growth)
A7: SaaS Subscriptions | B7: 18230 | C7: 28000 | D7: 58000 | E7: 115000 | F7: Organic growth only; no paid acq budget
A8: Coaching Programs | B8: 2000 | C8: 25000 | D8: 60000 | E8: 144000 | F8: Word of mouth; slower pipeline
A9: Events & Sales | B9: 73890 | C9: 75000 | D9: 100000 | E9: 140000 | F9: Fewer events; no cohost splits needed
A10: B2B / Sponsorships | B10: 0 | C10: 15000 | D10: 45000 | E10: 100000 | F10: Organic BD; fewer partner tiers
A11: Grants | B11: 69656 | C11: 40000 | D11: 25000 | E11: 10000 | F11: Continued grant pursuit
A12: Services & Consulting | B12: 48405 | C12: 20000 | D12: 0 | E12: 0 | F12: Wind down slowly to fund transition
A13: Total Revenue | B13: =SUM(B7:B12) -> 212181 | C13: =SUM(C7:C12) -> 203000 | D13: =SUM(D7:D12) -> 288000 | E13: =SUM(E7:E12) -> 509000
A15: EXPENSES (Lean Operations)
A16: COGS (9-10%) | B16: =-ABS(B13*0.093) -> -19732.833 | C16: =-ABS(C13*0.1) -> -20300 | D16: =-ABS(D13*0.1) -> -28800 | E16: =-ABS(E13*0.09) -> -45810
A17: Gross Profit | B17: =B13+B16 -> 192448.17 | C17: =C13+C16 -> 182700 | D17: =D13+D16 -> 259200 | E17: =E13+E16 -> 463190
A19: Founder Salary (Ila) | B19: 7911 | C19: 48000 | D19: 60000 | E19: 72000 | F19: Modest salary; grows with revenue
A20: Part-Time Contractor | B20: 2469 | C20: 15000 | D20: 24000 | E20: 36000 | F20: Dev/design help as needed
A21: Event Production & Pass-Through | B21: 25000 | C21: 50000 | D21: 65000 | E21: 80000 | F21: Fewer events, same cost structure
A22: General Business | B22: 15994 | C22: 18000 | D22: 20000 | E22: 25000 | F22: Lean overhead
A23: Software & Apps | B23: 8197 | C23: 12000 | D23: 15000 | E23: 20000 | F23: Essential tools only
A24: Marketing (Organic Focus) | B24: 5087 | C24: 10000 | D24: 15000 | E24: 25000 | F24: Social, content, community — no paid ads
A25: Legal & Accounting | B25: 3825 | C25: 6000 | D25: 8000 | E25: 12000 | F25: Basic compliance
A26: Travel & Meals | B26: 12116 | C26: 12000 | D26: 15000 | E26: 18000 | F26: Essential event travel only
A27: Benefits & Insurance | B27: 5341 | C27: 5000 | D27: 8000 | E27: 12000 | F27: Personal coverage
A28: Grant Expenses | B28: 5244 | C28: 5000 | D28: 8000 | E28: 10000 | F28: Micro-grants program
A29: Other | B29: 9116 | C29: 10000 | D29: 12000 | E29: 15000 | F29: Miscellaneous
A30: Total Operating Expenses | B30: =SUM(B19:B29) -> 100300 | C30: =SUM(C19:C29) -> 191000 | D30: =SUM(D19:D29) -> 250000 | E30: =SUM(E19:E29) -> 325000
A32: PROFITABILITY
A33: Operating Income | B33: =B17-B30 -> 92148.167 | C33: =C17-C30 -> -8300 | D33: =D17-D30 -> 9200 | E33: =E17-E30 -> 138190
A34: Operating Margin | B34: =IF(B13>0,B33/B13,0) -> 0.43429038 | C34: =IF(C13>0,C33/C13,0) -> -0.0408867 | D34: =IF(D13>0,D33/D13,0) -> 0.031944444 | E34: =IF(E13>0,E33/E13,0) -> 0.27149312
A36: Cash Position (EOY) | B36: =5000+B33 -> 97148.167 | C36: =B36+C33 -> 88848.167 | D36: =C36+D33 -> 98048.167 | E36: =D36+E33 -> 236238.17
A38: COMPARISON: BOOTSTRAPPED vs FUNDED
A39: Funded Total Revenue | B39: =Projections!B34 -> 194681 | C39: =Projections!C34 -> 315346 | D39: =Projections!D34 -> 797530 | E39: =Projections!E34 -> 1769500
A40: Bootstrapped Total Revenue | B40: =B13 -> 212181 | C40: =C13 -> 203000 | D40: =D13 -> 288000 | E40: =E13 -> 509000
A41: Revenue Difference | B41: =B39-B40 -> -17500 | C41: =C39-C40 -> 112346 | D41: =D39-D40 -> 509530 | E41: =E39-E40 -> 1260500
A43: Funded Operating Income | B43: =Projections!B39 -> 80575.667 | C43: =Projections!C39 -> -214188.6 | D43: =Projections!D39 -> -60223 | E43: =Projections!E39 -> 590245
A44: Bootstrapped Operating Income | B44: =B33 -> 92148.167 | C44: =C33 -> -8300 | D44: =D33 -> 9200 | E44: =E33 -> 138190
A46: Funded Cash (EOY) | B46: =Projections!B48 -> 85575.667 | C46: =Projections!C48 -> 331880.13 | D46: =Projections!D48 -> 208040.99 | E46: =Projections!E48 -> 686071.35
A47: Bootstrapped Cash (EOY) | B47: =B36 -> 97148.167 | C47: =C36 -> 88848.167 | D47: =D36 -> 98048.167 | E47: =E36 -> 236238.17
A49: KEY TAKEAWAY | B49: Bootstrapped = always profitable but slower growth. Funded = faster path to $1.8M but requires $500K raise and accepting a 2026 operating loss.

Sheet Valuation & Exit
A1: VALUATION & EXIT ANALYSIS
A2: Scenario modeling for SAFE, RBF, and CDFI fund structures
A3: 2025–2028 from Projections tab; 2029–2031 extrapolated at editable growth rate
B4: 2025 | C4: 2026 | D4: 2027 | E4: 2028 | F4: 2029 | G4: 2030 | H4: 2031 | I4: Notes
A5: REVENUE-BASED VALUATION
A6: Total Revenue | B6: =Projections!B34 -> 194681 | C6: =Projections!C34 -> 315346 | D6: =Projections!D34 -> 797530 | E6: =Projections!E34 -> 1769500 | F6: =E6*(1+B9) -> 2654250 | G6: =F6*(1+B9) -> 3981375 | H6: =G6*(1+B9) -> 5972062.5 | I6: 2029-2031 extrapolated at growth rate below
A7: Net Income | B7: =Projections!B45 -> 80575.667 | C7: =Projections!C45 -> -253695.54 | D7: =Projections!D45 -> -123839.14 | E7: =Projections!E45 -> 478030.36 | F7: =IF(E6>0,F6*(E7/E6),0) -> 717045.54 | G7: =IF(E6>0,G6*(E7/E6),0) -> 1075568.3 | H7: =IF(E6>0,H6*(E7/E6),0) -> 1613352.5 | I7: 2029-2031 assume 2028 net margin holds
A8: Revenue Growth Rate | C8: =IF(B6>0,(C6-B6)/B6,0) -> 0.61980882 | D8: =IF(C6>0,(D6-C6)/C6,0) -> 1.5290633 | E8: =IF(D6>0,(E6-D6)/D6,0) -> 1.2187253 | F8: =IF(E6>0,(F6-E6)/E6,0) -> 0.5 | G8: =IF(F6>0,(G6-F6)/F6,0) -> 0.5 | H8: =IF(G6>0,(H6-G6)/G6,0) -> 0.5
A9: Post-2028 Growth Rate (editable) | B9: 0.5 | I9: Change this to adjust 2029-2031 projections
A10: IMPLIED VALUATION (Revenue Multiple)
A11: Conservative (5x Revenue) | B11: =B6*5 -> 973405 | C11: =C6*5 -> 1576730 | D11: =D6*5 -> 3987650 | E11: =E6*5 -> 8847500 | F11: =F6*5 -> 13271250 | G11: =G6*5 -> 19906875 | H11: =H6*5 -> 29860312 | I11: Revenue x 5
A12: Moderate (8x Revenue) | B12: =B6*8 -> 1557448 | C12: =C6*8 -> 2522768 | D12: =D6*8 -> 6380240 | E12: =E6*8 -> 14156000 | F12: =F6*8 -> 21234000 | G12: =G6*8 -> 31851000 | H12: =H6*8 -> 47776500 | I12: Revenue x 8
A13: Aggressive (12x Revenue) | B13: =B6*12 -> 2336172 | C13: =C6*12 -> 3784152 | D13: =D6*12 -> 9570360 | E13: =E6*12 -> 21234000 | F13: =F6*12 -> 31851000 | G13: =G6*12 -> 47776500 | H13: =H6*12 -> 71664750 | I13: Revenue x 12
A14: High-Growth (15x Revenue) | B14: =B6*15 -> 2920215 | C14: =C6*15 -> 4730190 | D14: =D6*15 -> 11962950 | E14: =E6*15 -> 26542500 | F14: =F6*15 -> 39813750 | G14: =G6*15 -> 59720625 | H14: =H6*15 -> 89580938 | I14: Revenue x 15
A16: IMPLIED VALUATION (Net Income Multiple)
A17: Conservative (10x Net Income) | B17: =IF(B7>0,B7*10,0) -> 805756.67 | C17: =IF(C7>0,C7*10,0) -> 0 | D17: =IF(D7>0,D7*10,0) -> 0 | E17: =IF(E7>0,E7*10,0) -> 4780303.6 | F17: =IF(F7>0,F7*10,0) -> 7170455.4 | G17: =IF(G7>0,G7*10,0) -> 10755683 | H17: =IF(H7>0,H7*10,0) -> 16133525 | I17: Net income x 10 (if profitable)
A18: Moderate (15x Net Income) | B18: =IF(B7>0,B7*15,0) -> 1208635 | C18: =IF(C7>0,C7*15,0) -> 0 | D18: =IF(D7>0,D7*15,0) -> 0 | E18: =IF(E7>0,E7*15,0) -> 7170455.4 | F18: =IF(F7>0,F7*15,0) -> 10755683 | G18: =IF(G7>0,G7*15,0) -> 16133525 | H18: =IF(H7>0,H7*15,0) -> 24200287 | I18: Net income x 15 (if profitable)
A19: Aggressive (25x Net Income) | B19: =IF(B7>0,B7*25,0) -> 2014391.7 | C19: =IF(C7>0,C7*25,0) -> 0 | D19: =IF(D7>0,D7*25,0) -> 0 | E19: =IF(E7>0,E7*25,0) -> 11950759 | F19: =IF(F7>0,F7*25,0) -> 17926138 | G19: =IF(G7>0,G7*25,0) -> 26889208 | H19: =IF(H7>0,H7*25,0) -> 40333812 | I19: Net income x 25 (if profitable)
A21: SAFE INVESTOR SCENARIOS
A22: SAFE Investment Amount | B22: =Dashboard!B23 -> 250000 | C22: =B22 -> 250000 | D22: =B22 -> 250000 | E22: =B22 -> 250000 | F22: =B22 -> 250000 | G22: =B22 -> 250000 | H22: =B22 -> 250000 | I22: Driven by Dashboard fundraise inputs
A24: Scenario A: $3M Valuation Cap | I24: Fixed $3M cap (conservative)
A25: Equity Ownership % | B25: =IF(3000000>0,B22/3000000,0) -> 0.083333333 | C25: =IF(3000000>0,B22/3000000,0) -> 0.083333333 | D25: =IF(3000000>0,B22/3000000,0) -> 0.083333333 | E25: =IF(3000000>0,B22/3000000,0) -> 0.083333333 | F25: =IF(3000000>0,B22/3000000,0) -> 0.083333333 | G25: =IF(3000000>0,B22/3000000,0) -> 0.083333333 | H25: =IF(3000000>0,B22/3000000,0) -> 0.083333333 | I25: Investment / cap
A26: Payout at Moderate Exit (8x) | B26: =B25*B12 -> 129787.33 | C26: =C25*C12 -> 210230.67 | D26: =D25*D12 -> 531686.67 | E26: =E25*E12 -> 1179666.7 | F26: =F25*F12 -> 1769500 | G26: =G25*G12 -> 2654250 | H26: =H25*H12 -> 3981375 | I26: Equity % x 8x revenue valuation
A27: Payout at Aggressive Exit (12x) | B27: =B25*B13 -> 194681 | C27: =C25*C13 -> 315346 | D27: =D25*D13 -> 797530 | E27: =E25*E13 -> 1769500 | F27: =F25*F13 -> 2654250 | G27: =G25*G13 -> 3981375 | H27: =H25*H13 -> 5972062.5 | I27: Equity % x 12x revenue valuation
A28: Investor ROI (Moderate Exit) | B28: =IF(B22>0,B26/B22,0) -> 0.51914933 | C28: =IF(B22>0,C26/B22,0) -> 0.84092267 | D28: =IF(B22>0,D26/B22,0) -> 2.1267467 | E28: =IF(B22>0,E26/B22,0) -> 4.7186667 | F28: =IF(B22>0,F26/B22,0) -> 7.078 | G28: =IF(B22>0,G26/B22,0) -> 10.617 | H28: =IF(B22>0,H26/B22,0) -> 15.9255 | I28: Payout / investment
A29: Scenario B: Target Valuation Cap | I29: Driven by Dashboard cap input
A30: Equity Ownership % | B30: =IF(Dashboard!B32>0,B22/Dashboard!B32,0) -> 0.05 | C30: =IF(Dashboard!B32>0,B22/Dashboard!B32,0) -> 0.05 | D30: =IF(Dashboard!B32>0,B22/Dashboard!B32,0) -> 0.05 | E30: =IF(Dashboard!B32>0,B22/Dashboard!B32,0) -> 0.05 | F30: =IF(Dashboard!B32>0,B22/Dashboard!B32,0) -> 0.05 | G30: =IF(Dashboard!B32>0,B22/Dashboard!B32,0) -> 0.05 | H30: =IF(Dashboard!B32>0,B22/Dashboard!B32,0) -> 0.05 | I30: Investment / cap
A31: Payout at Moderate Exit (8x) | B31: =B30*B12 -> 77872.4 | C31: =C30*C12 -> 126138.4 | D31: =D30*D12 -> 319012 | E31: =E30*E12 -> 707800 | F31: =F30*F12 -> 1061700 | G31: =G30*G12 -> 1592550 | H31: =H30*H12 -> 2388825 | I31: Equity % x 8x revenue valuation
A32: Payout at Aggressive Exit (12x) | B32: =B30*B13 -> 116808.6 | C32: =C30*C13 -> 189207.6 | D32: =D30*D13 -> 478518 | E32: =E30*E13 -> 1061700 | F32: =F30*F13 -> 1592550 | G32: =G30*G13 -> 2388825 | H32: =H30*H13 -> 3583237.5 | I32: Equity % x 12x revenue valuation
A33: Investor ROI (Moderate Exit) | B33: =IF(B22>0,B31/B22,0) -> 0.3114896 | C33: =IF(B22>0,C31/B22,0) -> 0.5045536 | D33: =IF(B22>0,D31/B22,0) -> 1.276048 | E33: =IF(B22>0,E31/B22,0) -> 2.8312 | F33: =IF(B22>0,F31/B22,0) -> 4.2468 | G33: =IF(B22>0,G31/B22,0) -> 6.3702 | H33: =IF(B22>0,H31/B22,0) -> 9.5553 | I33: Payout / investment
A34: Scenario C: $8M Valuation Cap | I34: Fixed $8M cap (aggressive)
A35: Equity Ownership % | B35: =IF(8000000>0,B22/8000000,0) -> 0.03125 | C35: =IF(8000000>0,B22/8000000,0) -> 0.03125 | D35: =IF(8000000>0,B22/8000000,0) -> 0.03125 | E35: =IF(8000000>0,B22/8000000,0) -> 0.03125 | F35: =IF(8000000>0,B22/8000000,0) -> 0.03125 | G35: =IF(8000000>0,B22/8000000,0) -> 0.03125 | H35: =IF(8000000>0,B22/8000000,0) -> 0.03125 | I35: Investment / cap
A36: Payout at Moderate Exit (8x) | B36: =B35*B12 -> 48670.25 | C36: =C35*C12 -> 78836.5 | D36: =D35*D12 -> 199382.5 | E36: =E35*E12 -> 442375 | F36: =F35*F12 -> 663562.5 | G36: =G35*G12 -> 995343.75 | H36: =H35*H12 -> 1493015.6 | I36: Equity % x 8x revenue valuation
A37: Payout at Aggressive Exit (12x) | B37: =B35*B13 -> 73005.375 | C37: =C35*C13 -> 118254.75 | D37: =D35*D13 -> 299073.75 | E37: =E35*E13 -> 663562.5 | F37: =F35*F13 -> 995343.75 | G37: =G35*G13 -> 1493015.6 | H37: =H35*H13 -> 2239523.4 | I37: Equity % x 12x revenue valuation
A38: Investor ROI (Moderate Exit) | B38: =IF(B22>0,B36/B22,0) -> 0.194681 | C38: =IF(B22>0,C36/B22,0) -> 0.315346 | D38: =IF(B22>0,D36/B22,0) -> 0.79753 | E38: =IF(B22>0,E36/B22,0) -> 1.7695 | F38: =IF(B22>0,F36/B22,0) -> 2.65425 | G38: =IF(B22>0,G36/B22,0) -> 3.981375 | H38: =IF(B22>0,H36/B22,0) -> 5.9720625 | I38: Payout / investment
A39: REVENUE-BASED FINANCING (RBF)
A40: RBF Investment Amount | B40: =Dashboard!B24 -> 150000 | I40: Driven by Dashboard fundraise inputs
A41: Revenue Share % | B41: =Dashboard!B28 -> 0.05 | I41: Driven by Dashboard
A42: Repayment Cap (multiple) | B42: =Dashboard!B29 -> 1.5 | I42: Driven by Dashboard
A43: Max Repayment Amount | B43: =B40*B42 -> 225000 | I43: Investment x cap multiple
A45: Annual Revenue Share Payment | B45: =B6*B41 -> 9734.05 | C45: =C6*B41 -> 15767.3 | D45: =D6*B41 -> 39876.5 | E45: =E6*B41 -> 88475 | F45: =F6*B41 -> 132712.5 | G45: =G6*B41 -> 199068.75 | H45: =H6*B41 -> 298603.12 | I45: Revenue x share %
A46: Cumulative Payments | B46: =MIN(B45,B43) -> 9734.05 | C46: =MIN(B46+C45,B43) -> 25501.35 | D46: =MIN(C46+D45,B43) -> 65377.85 | E46: =MIN(D46+E45,B43) -> 153852.85 | F46: =MIN(E46+F45,B43) -> 225000 | G46: =MIN(F46+G45,B43) -> 225000 | H46: =MIN(G46+H45,B43) -> 225000 | I46: Capped at max repayment
A47: Remaining Balance | B47: =MAX(0,B43-B46) -> 215265.95 | C47: =MAX(0,B43-C46) -> 199498.65 | D47: =MAX(0,B43-D46) -> 159622.15 | E47: =MAX(0,B43-E46) -> 71147.15 | F47: =MAX(0,B43-F46) -> 0 | G47: =MAX(0,B43-G46) -> 0 | H47: =MAX(0,B43-H46) -> 0 | I47: Max repayment minus cumulative
A48: Fully Repaid? | B48: =IF(B47<=0,"YES","NO") -> NO | C48: =IF(C47<=0,"YES","NO") -> NO | D48: =IF(D47<=0,"YES","NO") -> NO | E48: =IF(E47<=0,"YES","NO") -> NO | F48: =IF(F47<=0,"YES","NO") -> YES | G48: =IF(G47<=0,"YES","NO") -> YES | H48: =IF(H47<=0,"YES","NO") -> YES
A50: CDFI LOAN SCENARIO
A51: CDFI Loan Amount | B51: =Dashboard!B25 -> 100000 | I51: Driven by Dashboard fundraise inputs
A52: Annual Interest Rate | B52: =Dashboard!B30 -> 0.06 | I52: Driven by Dashboard
A53: Loan Term (years) | B53: =Dashboard!B31 -> 5 | I53: Driven by Dashboard
A54: Annual Payment (PMT) | B54: =PMT(B52,B53,-B51) -> 23739.64 | I54: Fixed annual payment
A56: Annual Payment Due | B56: 0 | C56: =B54 -> 23739.64 | D56: =B54 -> 23739.64 | E56: =B54 -> 23739.64 | F56: =B54 -> 23739.64 | G56: =B54 -> 23739.64 | H56: 0 | I56: 5-year term: payments 2026-2030
A57: Cumulative Payments | B57: =B56 -> 0 | C57: =B57+C56 -> 23739.64 | D57: =C57+D56 -> 47479.28 | E57: =D57+E56 -> 71218.92 | F57: =E57+F56 -> 94958.56 | G57: =F57+G56 -> 118698.2 | H57: =G57+H56 -> 118698.2
A58: Total Interest Paid (over term) | B58: =B54*B53-B51 -> 18698.2 | I58: Total payments minus principal
A60: COMBINED FUND STRUCTURE SUMMARY
A61: Total Pre-Seed Raise | B61: =Dashboard!B26 -> 500000 | I61: From Dashboard fundraise scenario
A62: SAFE Portion | B62: =B22 -> 250000 | C62: =B22/B61 -> 0.5
A63: RBF Portion | B63: =B40 -> 150000 | C63: =B40/B61 -> 0.3
A64: CDFI Portion | B64: =B51 -> 100000 | C64: =B51/B61 -> 0.2
A66: Total Annual Debt Service (RBF+CDFI) | B66: =B45+B56 -> 9734.05 | C66: =C45+C56 -> 39506.94 | D66: =D45+D56 -> 63616.14 | E66: =E45+E56 -> 112214.64 | F66: =F45+F56 -> 156452.14 | G66: =G45+G56 -> 222808.39 | H66: =H45+H56 -> 298603.12 | I66: Cash outflow for debt repayment
A67: Debt Service as % of Revenue | B67: =IF(B6>0,B66/B6,0) -> 0.05 | C67: =IF(C6>0,C66/C6,0) -> 0.12528125 | D67: =IF(D6>0,D66/D6,0) -> 0.079766454 | E67: =IF(E6>0,E66/E6,0) -> 0.063416016 | F67: =IF(F6>0,F66/F6,0) -> 0.058944011 | G67: =IF(G6>0,G66/G6,0) -> 0.055962674 | H67: =IF(H6>0,H66/H6,0) -> 0.05
A69: SAFE Equity Dilution (target cap) | B69: =Dashboard!B34 -> 0.05 | I69: From Dashboard fundraise scenario
A70: Founder Ownership Retained | B70: =Dashboard!B38 -> 0.95
A72: M&A LANDSCAPE & STRATEGIC ACQUIRER ANALYSIS
A73: Cap table mapping of comparable companies, recent M&A transactions, and strategic acquirer candidates for Sengo.
A75: COMPARABLE COMPANY CAP TABLES
A76: Company | B76: Valuation | C76: Total Raised | D76: Lead / Key Investors | E76: Strategic Investors | F76: Status | I76: Acquisition Signal
A77: Hello Alice | B77: $130M | C77: $43.4M | D77: QED Investors, Serena Ventures, Backstage Capital, Golden Seeds, Harbert Growth | E77: Mastercard (co-developed Hello Alice Small Business Mastercard, $500M racial wealth gap pledge) | F77: Active / Growth | I77: Mastercard is deeply embedded — co-developed product, strategic investor. Natural acquirer to own SMB education + community.
A78: KingsCrowd | B78: $13.9M | C78: $22.6M | D78: Belvedere Strategic Capital, Startup Warrior, Netcapital, Triangle Tweener Fund, Tribal Ventures | E78: StartEngine (invested in Angel IV round); acquired CrowdCheck (Apr 2025) | F78: Independent | I78: Data/analytics layer for crowdfunding — acquisition target for Bloomberg, Carta, or any platform needing intelligence.
A79: Cherub | B79: N/D | C79: ~$2M | D79: Alli Webb (Dry Bar founder), Morgan DeBaun, angel investors | E79: None identified | F79: Pre-seed | I79: Angel matching with $950/yr subscription. ~$50K revenue vs Sengo's $212K. Acquisition target for AngelList or VC platforms.
A80: Republic | B80: N/D | C80: $214M | D80: Valor Equity Partners, Galaxy Interactive, Tribe Capital, Motley Fool Ventures, Prosus Ventures | E80: Morgan Stanley (investor) | F80: Active (acquired INX for $60M) | I80: Republic IS the acquirer — bought INX for tokenized securities. Traditional brokerages (Schwab, Robinhood) are logical buyers of Republic.
A81: StartEngine | B81: $1.38B | C81: $106M | D81: SE Agoura Investment (Aubrey Chernick), 9,000+ individual shareholders (Reg A+) | E81: Kevin O'Leary (strategic advisor & investor) | F81: Self-listed (Reg A+) | I81: Self-funded through own platform. No education layer — acquirer or partner for community/education bolt-on like Sengo.
A82: Carta | B82: $1.7B | C82: $1.16B | D82: Andreessen Horowitz, Spark Capital, Union Square Ventures, Lightspeed, Tiger Global, Thrive Capital | E82: Goldman Sachs Principal Strategic Investments | F82: Growth (acquired Vauban) | I82: Cap table infrastructure player. Goldman Sachs on cap table signals potential financial institution acquirer (GS, JPM, Blackstone).
A85: RECENT M&A TRANSACTIONS (Precedent Deals)
A86: Transaction | B86: Acquirer | C86: Target | D86: Deal Value | E86: Date | F86: Revenue Multiple | I86: Strategic Rationale
A87: Republic → INX | B87: Republic (OpenDeal) | C87: INX Digital Company | D87: $60M | E87: Apr 2025 | F87: N/A (crypto infra) | I87: Tokenized securities + regulated crypto trading. Republic owned 9.5% stake ($5.25M) before full acquisition.
A88: Carta → Vauban | B88: Carta | C88: Vauban (London) | D88: $80M+ | E88: Jun 2022 | F88: N/A (fund admin) | I88: Cross-border fund formation for SPVs. 50%+ of US SPVs have non-US LPs — Vauban solved international complexity.
A89: KingsCrowd → CrowdCheck | B89: KingsCrowd | C89: CrowdCheck | D89: N/D | E89: Apr 2025 | F89: N/A (compliance) | I89: Compliance + data analytics consolidation. Signals demand for intelligence layer in crowdfunding ecosystem.
A90: Schwab → Forge | B90: Charles Schwab | C90: Forge Global | D90: $1.9B | E90: Mar 2025 | F90: ~15x revenue | I90: Private market share trading for retail investors. Schwab expanding from public to private markets access.
A91: Hello Alice Series C | B91: N/A (fundraise) | C91: Hello Alice | D91: $130M val | E91: Apr 2024 | F91: 10.4x revenue | I91: Mastercard co-developed product. Identical B2B + community model to Sengo. Houston-based.
A92: Robinhood → Pluto | B92: Robinhood | C92: Pluto Capital | D92: N/D | E92: Jul 2024 | F92: N/A (AI research) | I92: AI-powered investment research platform. Signals Robinhood acquiring AI + education capabilities.
A95: SENGO STRATEGIC ACQUIRER CANDIDATES
A96: Who would acquire Sengo, and why? Mapped by acquirer category, strategic rationale, and precedent transaction.
A97: Acquirer Category | B97: Company | C97: Why They'd Acquire Sengo | D97: What Sengo Adds | E97: Precedent | F97: Est. Timing | I97: Deal Structure Likely
A98: Brokerage / WealthTech | B98: Charles Schwab | C98: Expanding from public → private markets. Already acquired Forge ($1.9B). Needs education + community layer to onboard retail investors into alternatives. | D98: AI-powered education, community trust, founder/funder network | E98: Schwab → Forge (Mar 2025) | F98: 2028–2030 | I98: Acquisition ($50–150M)
A99: Brokerage / WealthTech | B99: Robinhood | C99: Acquiring AI + education capabilities (bought Pluto Capital). Community-driven investing aligns with brand. Private markets = next growth vector. | D99: AI education platform, engaged community, private market access playbook | E99: Robinhood → Pluto Capital (Jul 2024) | F99: 2027–2029 | I99: Acqui-hire or acquisition ($30–100M)
A100: Crowdfunding Platform | B100: Republic / StartEngine | C100: Both lack education + community layers. Republic acquires capabilities (INX for $60M). StartEngine has 9K shareholders but no education infrastructure. | D100: Education-to-transaction pipeline, AI tools, community engagement, event infrastructure | E100: Republic → INX ($60M, Apr 2025) | F100: 2027–2028 | I100: Acquisition ($20–80M)
A101: Payment Network | B101: Mastercard / Visa | C101: Mastercard already invested in Hello Alice (identical model). Alternative assets expansion requires trusted community + education for emerging investors. | D101: Community-driven financial education, B2B sponsorship infrastructure, founder network | E101: Mastercard → Hello Alice (strategic investment + co-dev) | F101: 2028–2030 | I101: Strategic investment → acquisition ($50–200M)
A102: Financial Infrastructure | B102: Carta | C102: Cap table → fund admin → full private markets stack. Goldman Sachs on cap table. Education + community completes the retail investor onramp. | D102: Investor education, community deal flow, AI due diligence tools | E102: Carta → Vauban ($80M+, Jun 2022) | F102: 2028–2030 | I102: Acquisition ($40–120M)
A103: Financial Institution | B103: Goldman Sachs / JPMorgan | C103: Private markets democratization requires trusted education. Both launching retail alternatives products. Community + AI education = customer acquisition channel. | D103: Retail onramp for private markets, AI-powered education, diverse founder/funder network | E103: GS invested in Carta; JPM expanding Marcus platform | F103: 2029–2031 | I103: Acquisition or strategic partnership ($100M+)
A104: Data / Media | B104: Bloomberg / Yahoo Finance | C104: Financial data + education convergence. Bloomberg Terminal expanding to retail/alternatives. Private markets intelligence layer is gap in current offerings. | D104: AI-curated education, community data, private market deal flow intelligence | E104: KingsCrowd acquired CrowdCheck (data + compliance) | F104: 2028–2030 | I104: Acqui-hire or acquisition ($30–80M)
A105: Alt-Assets Platform | B105: iCapital / Forge / Moonfare | C105: Private market platforms need education to expand beyond accredited investors. Community trust layer converts retail investors that pure platforms can’t reach. | D105: Education-first funnel, community engagement, AI personalization, event infrastructure | E105: Schwab → Forge; iCapital scaling alternatives access | F105: 2027–2029 | I105: Acquisition ($30–100M)
A108: KEY TAKEAWAY
A109: Sengo sits at the intersection of three converging M&A themes: (1) private market democratization (Schwab→Forge), (2) AI-powered financial education (Robinhood→Pluto), and (3) community-driven capital platforms (Mastercard→Hello Alice). Every major acquirer category—brokerages, crowdfunding platforms, payment networks, financial institutions—is actively acquiring capabilities that Sengo already builds. The education + community + AI trust layer is the missing piece in every private markets platform stack.
A111: Signal to investors: At a $4–5M pre-seed cap, Sengo offers 8–30x return potential with multiple credible exit paths. The question isn’t whether education + community + private markets gets acquired—it’s which category of buyer moves first.
